setup.py
bg_probability/Binomialdistribution.py
bg_probability/Gaussiandistribution.py
bg_probability/Generaldistribution.py
bg_probability/__init__.py
bg_probability.egg-info/PKG-INFO
bg_probability.egg-info/SOURCES.txt
bg_probability.egg-info/dependency_links.txt
bg_probability.egg-info/not-zip-safe
bg_probability.egg-info/top_level.txt